digdir/__init__.py
digdir/main.py
digdir-0.1.0.dist-info/LICENSE
digdir-0.1.0.dist-info/METADATA
digdir-0.1.0.dist-info/WHEEL
digdir-0.1.0.dist-info/RECORD
