Metadata-Version: 2.1
Name: digdir
Version: 0.1.0
Summary: Digitaliseringsdirektoratet - Norwegian Digitalisation Agency
Author: Maged Helmy
Author-email: maged@newcode.ai
Requires-Python: >=3.11,<4.0
Classifier: License :: OSI Approved :: MIT License
Classifier: Operating System :: OS Independent
Classifier: Programming Language :: Python :: 3
Classifier: Programming Language :: Python :: 3.11
Classifier: Programming Language :: Python :: 3.12
